LICENSE
README.md
setup.cfg
setup.py
stepizer/__init__.py
stepizer/loader.py
stepizer/proxy.py
stepizer/register.py
stepizer/step.py
stepizer.egg-info/PKG-INFO
stepizer.egg-info/SOURCES.txt
stepizer.egg-info/dependency_links.txt
stepizer.egg-info/requires.txt
stepizer.egg-info/top_level.txt
tests/__init__.py
tests/benchmark/__init__.py
tests/benchmark/test_execution_time.py
tests/benchmark/utils.py
tests/integration/__init__.py
tests/integration/test_pipeline.py
tests/unit/__init__.py
tests/unit/test_step.py