Metadata-Version: 2.1
Name: stepizer
Version: 0.2.1
Summary: The tool for better organization of the workflow.
Home-page: https://gitlab.com/mateusz.baran/stepizer
Author: Mateusz Baran
Author-email: mateusz.baran.sanok@gmail.com
Maintainer: Mateusz Baran
Maintainer-email: mateusz.baran.sanok@gmail.com
License: MIT
Platform: UNKNOWN
Classifier: Development Status :: 3 - Alpha
Classifier: Programming Language :: Python
Classifier: Programming Language :: Python :: 3
Classifier: Programming Language :: Python :: 3.8
Classifier: Programming Language :: Python :: 3.9
Classifier: Operating System :: OS Independent
Classifier: License :: OSI Approved :: MIT License
Requires-Python: >=3.8, <4
Provides-Extra: dev
License-File: LICENSE
